macls/__init__.py
macls/predict.py
macls/trainer.py
macls/configs/augmentation.yml
macls/configs/cam++.yml
macls/configs/ecapa_tdnn.yml
macls/configs/eres2net.yml
macls/configs/panns.yml
macls/configs/res2net.yml
macls/configs/resnet_se.yml
macls/configs/tdnn.yml
macls/data_utils/__init__.py
macls/data_utils/collate_fn.py
macls/data_utils/featurizer.py
macls/data_utils/reader.py
macls/metric/__init__.py
macls/metric/metrics.py
macls/models/__init__.py
macls/models/campplus.py
macls/models/ecapa_tdnn.py
macls/models/eres2net.py
macls/models/panns.py
macls/models/pooling.py
macls/models/res2net.py
macls/models/resnet_se.py
macls/models/tdnn.py
macls/models/utils.py
macls/optimizer/__init__.py
macls/optimizer/scheduler.py
macls/utils/__init__.py
macls/utils/checkpoint.py
macls/utils/record.py
macls/utils/utils.py
macls-1.0.6.dist-info/LICENSE
macls-1.0.6.dist-info/METADATA
macls-1.0.6.dist-info/WHEEL
macls-1.0.6.dist-info/top_level.txt
macls-1.0.6.dist-info/RECORD
